edgy_guardian/__init__.py
edgy_guardian/apps.py
edgy_guardian/configs.py
edgy_guardian/enums.py
edgy_guardian/exceptions.py
edgy_guardian/loader.py
edgy_guardian/mixins.py
edgy_guardian/py.typed
edgy_guardian/shortcuts.py
edgy_guardian/utils.py
edgy_guardian/_internal/__init__.py
edgy_guardian/_internal/_models.py
edgy_guardian/_internal/_module_loading.py
edgy_guardian/content_types/__init__.py
edgy_guardian/content_types/apps.py
edgy_guardian/content_types/managers.py
edgy_guardian/content_types/models.py
edgy_guardian/content_types/utils.py
edgy_guardian/permissions/__init__.py
edgy_guardian/permissions/apps.py
edgy_guardian/permissions/exceptions.py
edgy_guardian/permissions/managers.py
edgy_guardian/permissions/models.py
edgy_guardian-0.4.0.dist-info/METADATA
edgy_guardian-0.4.0.dist-info/WHEEL
edgy_guardian-0.4.0.dist-info/licenses/LICENSE
edgy_guardian-0.4.0.dist-info/RECORD
