Metadata-Version: 2.4
Name: edgy_guardian
Version: 0.4.0
Summary: Per object permissions for Edgy
Project-URL: Homepage, https://github.com/dymmond/edgy-guardian
Project-URL: Documentation, https://edgy-guardian.dymmond.com
Project-URL: Changelog, https://edgy-guardian.dymmond.com/release-notes/
Project-URL: Funding, https://github.com/sponsors/tarsil
Project-URL: Source, https://github.com/dymmond/edgy-guardian
Author-email: Tiago Silva <tiago.arasilva@gmail.com>
License-File: LICENSE
Keywords: edgy_guardian
Classifier: Development Status :: 4 - Beta
Classifier: Environment :: Web Environment
Classifier: Framework :: AnyIO
Classifier: Framework :: AsyncIO
Classifier: Intended Audience :: Developers
Classifier: Intended Audience :: Information Technology
Classifier: Intended Audience :: System Administrators
Classifier: License :: OSI Approved :: BSD License
Classifier: Operating System :: OS Independent
Classifier: Programming Language :: Python
Classifier: Programming Language :: Python :: 3
Classifier: Programming Language :: Python :: 3 :: Only
Classifier: Programming Language :: Python :: 3.10
Classifier: Programming Language :: Python :: 3.11
Classifier: Programming Language :: Python :: 3.12
Classifier: Programming Language :: Python :: 3.13
Classifier: Topic :: Internet
Classifier: Topic :: Internet :: WWW/HTTP
Classifier: Topic :: Internet :: WWW/HTTP :: HTTP Servers
Classifier: Topic :: Software Development
Classifier: Topic :: Software Development :: Libraries
Classifier: Topic :: Software Development :: Libraries :: Application Frameworks
Classifier: Topic :: Software Development :: Libraries :: Python Modules
Classifier: Typing :: Typed
Requires-Python: >=3.10
Requires-Dist: edgy<1.0.0,>=0.31.1
Provides-Extra: testing
Requires-Dist: autoflake<3.0.0,>=2.0.2; extra == 'testing'
Requires-Dist: black<25.0,==24.1.1; extra == 'testing'
Requires-Dist: edgy[postgres,testing]<1.0.0,>=0.27.3; extra == 'testing'
Requires-Dist: esmerald>=3.8.4; extra == 'testing'
Requires-Dist: faker; extra == 'testing'
Requires-Dist: httpx; extra == 'testing'
Requires-Dist: isort<6.0.0,>=5.12.0; extra == 'testing'
Requires-Dist: pytest-cov<5.0.0,>=4.0.0; extra == 'testing'
Requires-Dist: pytest-pspec; extra == 'testing'
Requires-Dist: pytest<9.0.0,>=7.2.2; extra == 'testing'
